{
  "$schema": "https://developer.microsoft.com/json-schemas/fabric/item/report/definition/visualContainer/2.10.0/schema.json",
  "name": "fdc396f06a477aded4ea",
  "position": {
    "x": 31.560997671652792,
    "y": 282.67676175480329,
    "z": 2000,
    "height": 424.01514263220491,
    "width": 1228.1344746143152,
    "tabOrder": 2000
  },
  "visual": {
    "visualType": "scatterChart",
    "query": {
      "queryState": {
        "Series": {
          "projections": [
            {
              "field": {
                "Column": {
                  "Expression": {
                    "SourceRef": {
                      "Entity": "Restaurants"
                    }
                  },
                  "Property": "Cost Bucket"
                }
              },
              "queryRef": "Restaurants.Cost Bucket",
              "nativeQueryRef": "Cost Bucket"
            }
          ]
        },
        "Size": {
          "projections": [
            {
              "field": {
                "Aggregation": {
                  "Expression": {
                    "Column": {
                      "Expression": {
                        "SourceRef": {
                          "Entity": "Restaurants"
                        }
                      },
                      "Property": "Costfor two"
                    }
                  },
                  "Function": 1
                }
              },
              "queryRef": "CountNonNull(Restaurants.Costfor two)",
              "nativeQueryRef": "Average of Costfor two"
            }
          ]
        },
        "Tooltips": {
          "projections": [
            {
              "field": {
                "Aggregation": {
                  "Expression": {
                    "Column": {
                      "Expression": {
                        "SourceRef": {
                          "Entity": "Restaurants"
                        }
                      },
                      "Property": "name"
                    }
                  },
                  "Function": 3
                }
              },
              "queryRef": "Min(Restaurants.name)",
              "nativeQueryRef": "First name"
            }
          ]
        },
        "X": {
          "projections": [
            {
              "field": {
                "Column": {
                  "Expression": {
                    "SourceRef": {
                      "Entity": "Restaurants"
                    }
                  },
                  "Property": "rate"
                }
              },
              "queryRef": "Restaurants.rate",
              "nativeQueryRef": "rate",
              "active": true
            }
          ]
        },
        "Y": {
          "projections": [
            {
              "field": {
                "Measure": {
                  "Expression": {
                    "SourceRef": {
                      "Entity": "KPI"
                    }
                  },
                  "Property": "Selected KPI Value"
                }
              },
              "queryRef": "KPI.Selected KPI Value",
              "nativeQueryRef": "Selected KPI Value"
            }
          ]
        }
      }
    },
    "objects": {
      "valueAxis": [
        {
          "properties": {
            "showAxisTitle": {
              "expr": {
                "Literal": {
                  "Value": "false"
                }
              }
            },
            "show": {
              "expr": {
                "Literal": {
                  "Value": "false"
                }
              }
            }
          }
        }
      ],
      "categoryAxis": [
        {
          "properties": {
            "showAxisTitle": {
              "expr": {
                "Literal": {
                  "Value": "false"
                }
              }
            },
            "axisType": {
              "expr": {
                "Literal": {
                  "Value": "'Categorical'"
                }
              }
            },
            "show": {
              "expr": {
                "Literal": {
                  "Value": "false"
                }
              }
            },
            "titleColor": {
              "solid": {
                "color": {
                  "expr": {
                    "ThemeDataColor": {
                      "ColorId": 0,
                      "Percent": 0
                    }
                  }
                }
              }
            }
          }
        }
      ],
      "dataPoint": [
        {
          "properties": {
            "fill": {
              "solid": {
                "color": {
                  "expr": {
                    "ThemeDataColor": {
                      "ColorId": 9,
                      "Percent": 0
                    }
                  }
                }
              }
            }
          }
        },
        {
          "properties": {
            "fill": {
              "solid": {
                "color": {
                  "expr": {
                    "Literal": {
                      "Value": "'#F97000'"
                    }
                  }
                }
              }
            }
          },
          "selector": {
            "data": [
              {
                "scopeId": {
                  "Comparison": {
                    "ComparisonKind": 0,
                    "Left": {
                      "Column": {
                        "Expression": {
                          "SourceRef": {
                            "Entity": "Restaurants"
                          }
                        },
                        "Property": "Cost Bucket"
                      }
                    },
                    "Right": {
                      "Literal": {
                        "Value": "'Budget Friendly'"
                      }
                    }
                  }
                }
              }
            ]
          }
        },
        {
          "properties": {
            "fill": {
              "solid": {
                "color": {
                  "expr": {
                    "Literal": {
                      "Value": "'#03FD00'"
                    }
                  }
                }
              }
            }
          },
          "selector": {
            "data": [
              {
                "scopeId": {
                  "Comparison": {
                    "ComparisonKind": 0,
                    "Left": {
                      "Column": {
                        "Expression": {
                          "SourceRef": {
                            "Entity": "Restaurants"
                          }
                        },
                        "Property": "Cost Bucket"
                      }
                    },
                    "Right": {
                      "Literal": {
                        "Value": "'Mid Range'"
                      }
                    }
                  }
                }
              }
            ]
          }
        },
        {
          "properties": {
            "fill": {
              "solid": {
                "color": {
                  "expr": {
                    "Literal": {
                      "Value": "'#F507E1'"
                    }
                  }
                }
              }
            }
          },
          "selector": {
            "data": [
              {
                "scopeId": {
                  "Comparison": {
                    "ComparisonKind": 0,
                    "Left": {
                      "Column": {
                        "Expression": {
                          "SourceRef": {
                            "Entity": "Restaurants"
                          }
                        },
                        "Property": "Cost Bucket"
                      }
                    },
                    "Right": {
                      "Literal": {
                        "Value": "'Premium'"
                      }
                    }
                  }
                }
              }
            ]
          }
        }
      ],
      "legend": [
        {
          "properties": {
            "labelColor": {
              "solid": {
                "color": {
                  "expr": {
                    "ThemeDataColor": {
                      "ColorId": 0,
                      "Percent": 0
                    }
                  }
                }
              }
            },
            "position": {
              "expr": {
                "Literal": {
                  "Value": "'BottomCenter'"
                }
              }
            }
          }
        }
      ]
    },
    "visualContainerObjects": {
      "title": [
        {
          "properties": {
            "show": {
              "expr": {
                "Literal": {
                  "Value": "true"
                }
              }
            },
            "text": {
              "expr": {
                "Aggregation": {
                  "Expression": {
                    "Column": {
                      "Expression": {
                        "SourceRef": {
                          "Entity": "KPI"
                        }
                      },
                      "Property": "KPI Name"
                    }
                  },
                  "Function": 3
                }
              }
            },
            "alignment": {
              "expr": {
                "Literal": {
                  "Value": "'center'"
                }
              }
            },
            "fontColor": {
              "solid": {
                "color": {
                  "expr": {
                    "ThemeDataColor": {
                      "ColorId": 0,
                      "Percent": 0
                    }
                  }
                }
              }
            },
            "bold": {
              "expr": {
                "Literal": {
                  "Value": "true"
                }
              }
            }
          }
        }
      ],
      "visualHeader": [
        {
          "properties": {
            "border": {
              "solid": {
                "color": {
                  "expr": {
                    "ThemeDataColor": {
                      "ColorId": 0,
                      "Percent": 0
                    }
                  }
                }
              }
            }
          }
        }
      ],
      "border": [
        {
          "properties": {
            "show": {
              "expr": {
                "Literal": {
                  "Value": "true"
                }
              }
            },
            "radius": {
              "expr": {
                "Literal": {
                  "Value": "5D"
                }
              }
            },
            "color": {
              "solid": {
                "color": {
                  "expr": {
                    "ThemeDataColor": {
                      "ColorId": 9,
                      "Percent": 0
                    }
                  }
                }
              }
            }
          }
        }
      ],
      "padding": [
        {
          "properties": {
            "top": {
              "expr": {
                "Literal": {
                  "Value": "5D"
                }
              }
            }
          }
        }
      ],
      "background": [
        {
          "properties": {
            "color": {
              "solid": {
                "color": {
                  "expr": {
                    "ThemeDataColor": {
                      "ColorId": 2,
                      "Percent": -0.5
                    }
                  }
                }
              }
            }
          }
        }
      ]
    },
    "drillFilterOtherVisuals": true
  },
  "filterConfig": {
    "filters": [
      {
        "name": "2a0c54b8c07d91174b4d",
        "field": {
          "Column": {
            "Expression": {
              "SourceRef": {
                "Entity": "Restaurants"
              }
            },
            "Property": "rate"
          }
        },
        "type": "Categorical",
        "filter": {
          "Version": 2,
          "From": [
            {
              "Name": "r",
              "Entity": "Restaurants",
              "Type": 0
            }
          ],
          "Where": [
            {
              "Condition": {
                "Not": {
                  "Expression": {
                    "In": {
                      "Expressions": [
                        {
                          "Column": {
                            "Expression": {
                              "SourceRef": {
                                "Source": "r"
                              }
                            },
                            "Property": "rate"
                          }
                        }
                      ],
                      "Values": [
                        [
                          {
                            "Literal": {
                              "Value": "null"
                            }
                          }
                        ]
                      ]
                    }
                  }
                }
              }
            }
          ]
        },
        "objects": {
          "general": [
            {
              "properties": {
                "isInvertedSelectionMode": {
                  "expr": {
                    "Literal": {
                      "Value": "true"
                    }
                  }
                }
              }
            }
          ]
        }
      }
    ]
  }
}